user_info_collector/__init__.py
user_info_collector/collect.py
user_info_collector-0.1.0.dist-info/licenses/LICENSE
user_info_collector-0.1.0.dist-info/METADATA
user_info_collector-0.1.0.dist-info/WHEEL
user_info_collector-0.1.0.dist-info/entry_points.txt
user_info_collector-0.1.0.dist-info/top_level.txt
user_info_collector-0.1.0.dist-info/RECORD
